AgentLogin
